rpm_spec_dependency_analyzer/__init__.py
rpm_spec_dependency_analyzer/__main__.py
rpm_spec_dependency_analyzer/pyrpm_spec.py
rpm_spec_dependency_analyzer/rpm_spec_dependency_analyzer.py
rpm_spec_dependency_analyzer-0.5.dist-info/DESCRIPTION.rst
rpm_spec_dependency_analyzer-0.5.dist-info/METADATA
rpm_spec_dependency_analyzer-0.5.dist-info/RECORD
rpm_spec_dependency_analyzer-0.5.dist-info/WHEEL
rpm_spec_dependency_analyzer-0.5.dist-info/entry_points.txt
rpm_spec_dependency_analyzer-0.5.dist-info/metadata.json
rpm_spec_dependency_analyzer-0.5.dist-info/top_level.txt
