Metadata-Version: 2.0
Name: rpm-spec-dependency-analyzer
Version: 0.5
Summary: Module for analyzing RPM spec dependencies.
Home-page: https://github.com/f18m/rpm-spec-dependency-analyzer
Author: Francesco Montorsi
Author-email: francesco.montorsi@gmail.com
License: UNKNOWN
Download-URL: https://github.com/f18m/rpm-spec-dependency-analyzer/archive/1.0.tar.gz
Keywords: RPM,spec,graphviz,dependencies,dependency-analysis
Platform: UNKNOWN
Classifier: Programming Language :: Python :: 3
Requires-Python: >=3
